rein/__init__.py
rein/cli.py
rein/xuc.py
rein/api/__init__.py
rein/api/crypto/__init__.py
rein/api/crypto/rest.py
rein/api/okex/__init__.py
rein/api/okex/error_code.py
rein/api/okex/realtime.py
rein/api/okex/trade.py
rein/api/onetoken/__init__.py
rein/api/onetoken/master.py
rein/api/quote/__init__.py
rein/api/quote/historical.py
rein/api/quote/master.py
rein/api/quote/realtime.py
rein/api/trade/__init__.py
rein/client/__init__.py
rein/util/__init__.py
rein/util/log.py
rein/util/model.py
rein/util/persistence.py
rein/util/protocol.py
rein/util/rest.py
rein/util/serialzation.py
rein-0.1.0.dist-info/METADATA
rein-0.1.0.dist-info/RECORD
rein-0.1.0.dist-info/WHEEL
rein-0.1.0.dist-info/top_level.txt
