Metadata-Version: 2.1
Name: rein
Version: 0.1.0
Summary: lightweight trading platform
Home-page: https://github.com/chrischen3121/rein
Author: Chris Chen
Author-email: chrischen3121@gmail.com
License: Apache Software License 2.0
Keywords: rein
Platform: UNKNOWN
Classifier: Development Status :: 2 - Pre-Alpha
Classifier: Intended Audience :: Developers
Classifier: License :: OSI Approved :: Apache Software License
Classifier: Natural Language :: English
Classifier: Programming Language :: Python :: 3.5
Classifier: Programming Language :: Python :: 3.6
Classifier: Programming Language :: Python :: 3.7
Requires-Python: >=3.5.3
Requires-Dist: click (>=6.7)
Requires-Dist: python-dateutil (>=2.7.3)
Requires-Dist: autobahn (>=18.6.1)
Requires-Dist: Twisted (>=18.7.0)
Requires-Dist: blinker (>=1.4)
Requires-Dist: pyOpenSSL (>=18.0.0)
Requires-Dist: bidict (>=0.17.2)
Requires-Dist: namedlist (>=1.7)
Requires-Dist: aiohttp (>=2.3.10)
Requires-Dist: requests (>=2.19.1)
Requires-Dist: SQLAlchemy (>=1.2.10)
Requires-Dist: mysql-connector (>=2.1.6)
